setup.cfg
setup.py
kakaoplus/__init__.py
kakaoplus/base.py
kakaoplus/kakaoplus.py
kakaoplus/payload.py
kakaoplus/template.py
kakaoplus/utils.py
kakaoplus.egg-info/PKG-INFO
kakaoplus.egg-info/SOURCES.txt
kakaoplus.egg-info/dependency_links.txt
kakaoplus.egg-info/top_level.txt