Metadata-Version: 1.1
Name: kakaoplus
Version: 0.0.2
Summary: A Python Library For Kakao Plus Friend Auto Reply API
Home-page: https://github.com/HwangWonYo/kakaoplus
Author: wonyoHwang
Author-email: hollal0726@gmail.com
License: MIT License
Keywords: kakao,plus friend,chatbot
Platform: UNKNOWN
Classifier: Development Status :: 3 - Alpha
Classifier: Intended Audience :: Developers
Classifier: Programming Language :: Python
Classifier: Programming Language :: Python :: 2.7
Classifier: Programming Language :: Python :: 3
Classifier: License :: OSI Approved :: MIT License
